LICENSE.md
MANIFEST.in
README.md
setup.py
gfdlfremake/__init__.py
gfdlfremake/buildBaremetal.py
gfdlfremake/buildDocker.py
gfdlfremake/checkout.py
gfdlfremake/fremake
gfdlfremake/makefilefre.py
gfdlfremake/platformfre.py
gfdlfremake/schema.json
gfdlfremake/targetfre.py
gfdlfremake/varsfre.py
gfdlfremake/yamlfre.py
gfdlfremake.egg-info/PKG-INFO
gfdlfremake.egg-info/SOURCES.txt
gfdlfremake.egg-info/dependency_links.txt
gfdlfremake.egg-info/requires.txt
gfdlfremake.egg-info/top_level.txt
gfdlfremake/yamls/am5.yaml
gfdlfremake/yamls/compile.yaml
gfdlfremake/yamls/platforms.yaml
gfdlfremake/yamls/schema.json